{
 "2000":{
  "Afghanistan":"19500000",
  "Bangladesh":"129000000",
  "Cambodia":"12100000",
  "Ethiopia":"67000000",
  "Senegal":"9700000"
 },
 "2001":{
  "Afghanistan":"19700000",
  "Bangladesh":"132000000",
  "Cambodia":"12300000",
  "Ethiopia":"69000000",
  "Senegal":"9940000"
 },
 "2002":{
  "Afghanistan":"21000000",
  "Bangladesh":"134000000",
  "Cambodia":"12600000",
  "Ethiopia":"71100000",
  "Senegal":"10200000"
 },
 "2003":{
  "Afghanistan":"22600000",
  "Bangladesh":"137000000",
  "Cambodia":"12800000",
  "Ethiopia":"73200000",
  "Senegal":"10400000"
 },
 "2004":{
  "Afghanistan":"23600000",
  "Bangladesh":"139000000",
  "Cambodia":"13000000",
  "Ethiopia":"75300000",
  "Senegal":"10700000"
 },
 "2005":{
  "Afghanistan":"24400000",
  "Bangladesh":"141000000",
  "Cambodia":"13200000",
  "Ethiopia":"77500000",
  "Senegal":"11000000"
 },
 "2006":{
  "Afghanistan":"25400000",
  "Bangladesh":"143000000",
  "Cambodia":"13500000",
  "Ethiopia":"79700000",
  "Senegal":"11300000"
 },
 "2007":{
  "Afghanistan":"25900000",
  "Bangladesh":"144000000",
  "Cambodia":"13700000",
  "Ethiopia":"82000000",
  "Senegal":"11600000"
 },
 "2008":{
  "Afghanistan":"26400000",
  "Bangladesh":"145000000",
  "Cambodia":"13900000",
  "Ethiopia":"84400000",
  "Senegal":"11900000"
 },
 "2009":{
  "Afghanistan":"27400000",
  "Bangladesh":"147000000",
  "Cambodia":"14200000",
  "Ethiopia":"86800000",
  "Senegal":"12200000"
 },
 "2010":{
  "Afghanistan":"28200000",
  "Bangladesh":"148000000",
  "Cambodia":"14400000",
  "Ethiopia":"89200000",
  "Senegal":"12500000"
 },
 "2011":{
  "Afghanistan":"29200000",
  "Bangladesh":"150000000",
  "Cambodia":"14600000",
  "Ethiopia":"91800000",
  "Senegal":"12900000"
 },
 "2012":{
  "Afghanistan":"30500000",
  "Bangladesh":"152000000",
  "Cambodia":"14800000",
  "Ethiopia":"94500000",
  "Senegal":"13200000"
 },
 "2013":{
  "Afghanistan":"31500000",
  "Bangladesh":"154000000",
  "Cambodia":"15000000",
  "Ethiopia":"97100000",
  "Senegal":"13600000"
 },
 "2014":{
  "Afghanistan":"32700000",
  "Bangladesh":"156000000",
  "Cambodia":"15200000",
  "Ethiopia":"99700000",
  "Senegal":"14000000"
 },
 "2015":{
  "Afghanistan":"33800000",
  "Bangladesh":"158000000",
  "Cambodia":"15400000",
  "Ethiopia":"102000000",
  "Senegal":"14400000"
 },
 "2016":{
  "Afghanistan":"34600000",
  "Bangladesh":"160000000",
  "Cambodia":"15600000",
  "Ethiopia":"105000000",
  "Senegal":"14800000"
 },
 "2017":{
  "Afghanistan":"35600000",
  "Bangladesh":"162000000",
  "Cambodia":"15800000",
  "Ethiopia":"108000000",
  "Senegal":"15200000"
 },
 "2018":{
  "Afghanistan":"36700000",
  "Bangladesh":"164000000",
  "Cambodia":"16000000",
  "Ethiopia":"111000000",
  "Senegal":"15600000"
 },
 "2019":{
  "Afghanistan":"37800000",
  "Bangladesh":"166000000",
  "Cambodia":"16200000",
  "Ethiopia":"114000000",
  "Senegal":"16000000"
 }
}